marun/App.py
marun/Conf.py
marun/Consts.py
marun/Java.py
marun/__init__.py
marun/marun.py
marun/sub_get.py
marun/sub_init.py
marun/sub_install.py
marun/sub_run.py
marun/util.py
marun-0.1.1.dist-info/LICENSE
marun-0.1.1.dist-info/METADATA
marun-0.1.1.dist-info/WHEEL
marun-0.1.1.dist-info/entry_points.txt
marun-0.1.1.dist-info/top_level.txt
marun-0.1.1.dist-info/RECORD
