Metadata-Version: 2.1
Name: marun
Version: 0.1.1
Summary: get an artifact and dependencies (java jar files) from maven repositories, like pip in python.
Home-page: https://github.com/nishemon/marun
Author: Shinya Takai
Author-email: shtk@cccis.jp
License: MIT
Keywords: java,maven,deploy,ivy,repository,package,artifact,run
Platform: UNKNOWN
Classifier: Development Status :: 2 - Pre-Alpha
Classifier: Environment :: Console
Classifier: Operating System :: POSIX
Classifier: Programming Language :: Java
Classifier: Programming Language :: Python :: 2.7
Classifier: License :: OSI Approved :: MIT License
Requires-Python: >=2.7, <3
